ferrox/__init__.py
ferrox/_ferrox.abi3.so
ferrox/_ferrox.pyi
ferrox/py.typed
ferrox-0.0.3.dist-info/METADATA
ferrox-0.0.3.dist-info/WHEEL
ferrox-0.0.3.dist-info/RECORD
