Metadata-Version: 2.4
Name: ferrox
Version: 0.0.3
Classifier: Development Status :: 3 - Alpha
Classifier: Intended Audience :: Science/Research
Classifier: License :: OSI Approved :: MIT License
Classifier: Programming Language :: Python :: 3
Classifier: Programming Language :: Python :: 3.11
Classifier: Programming Language :: Python :: 3.12
Classifier: Programming Language :: Python :: 3.13
Classifier: Programming Language :: Rust
Classifier: Topic :: Scientific/Engineering :: Chemistry
Classifier: Topic :: Scientific/Engineering :: Physics
Requires-Dist: pymatgen>=2025.10.7 ; extra == 'dev'
Requires-Dist: pytest>=8.0 ; extra == 'dev'
Provides-Extra: dev
Summary: High-performance structure matching for crystallographic data
Keywords: crystallography,materials-science,pymatgen,structure-matching
Author-email: Janosh Riebesell <janosh@lbl.gov>
License: MIT
Requires-Python: >=3.11
Project-URL: Repository, https://github.com/janosh/matterviz
